.gitignore
AUTHORS
COPYING
MANIFEST.in
Makefile
README
config.xml
setup.py
admin/Manifest.json
admin/config.json
admin/generate.py
admin/api/resource/apiviewer/image/information18.png
admin/api/resource/apiviewer/image/search18.png
admin/api/resource/qx/decoration/Modern/app-header.png
admin/api/resource/qx/decoration/Modern/arrows-combined.png
admin/api/resource/qx/decoration/Modern/button-lr-combined.png
admin/api/resource/qx/decoration/Modern/button-tb-combined.png
admin/api/resource/qx/decoration/Modern/groupbox-lr-combined.png
admin/api/resource/qx/decoration/Modern/groupbox-tb-combined.png
admin/api/resource/qx/decoration/Modern/inputcheckradio-combined.png
admin/api/resource/qx/decoration/Modern/menu-background-combined.png
admin/api/resource/qx/decoration/Modern/pane-lr-combined.png
admin/api/resource/qx/decoration/Modern/pane-tb-combined.png
admin/api/resource/qx/decoration/Modern/scrollbar-combined.png
admin/api/resource/qx/decoration/Modern/selection.png
admin/api/resource/qx/decoration/Modern/shadow-lr-combined.png
admin/api/resource/qx/decoration/Modern/shadow-small-lr-combined.png
admin/api/resource/qx/decoration/Modern/shadow-small-tb-combined.png
admin/api/resource/qx/decoration/Modern/shadow-tb-combined.png
admin/api/resource/qx/decoration/Modern/splitpane-knobs-combined.png
admin/api/resource/qx/decoration/Modern/table-combined.png
admin/api/resource/qx/decoration/Modern/tabview-button-bottom-active-lr-combined.png
admin/api/resource/qx/decoration/Modern/tabview-button-bottom-active-tb-combined.png
admin/api/resource/qx/decoration/Modern/tabview-button-bottom-inactive-b-combined.png
admin/api/resource/qx/decoration/Modern/tabview-button-bottom-inactive-lr-combined.png
admin/api/resource/qx/decoration/Modern/tabview-button-bottom-inactive-t-combined.png
admin/api/resource/qx/decoration/Modern/tabview-button-left-active-lr-combined.png
admin/api/resource/qx/decoration/Modern/tabview-button-left-active-tb-combined.png
spamfighter.egg-info/PKG-INFO
spamfighter.egg-info/SOURCES.txt
spamfighter.egg-info/dependency_links.txt
spamfighter.egg-info/entry_points.txt
spamfighter.egg-info/not-zip-safe
spamfighter.egg-info/requires.txt
spamfighter.egg-info/top_level.txt
