Metadata-Version: 1.0
Name: spamfighter
Version: 0.2.0
Summary: Web-service fighting spam and other unsolicited messages
Home-page: http://spam-fighter.ru/
Author: Andrey Smirnov
Author-email: me@smira.ru
License: GNU GPL
Download-URL: http://spam-fighter.ru/rus/Downloads
Keywords: spam api
Platform: UNKNOWN
Classifier: Development Status :: 3 - Alpha
Classifier: Environment :: Web Environment
Classifier: Environment :: No Input/Output (Daemon)
Classifier: Framework :: Twisted
Classifier: Intended Audience :: Developers
Classifier: Intended Audience :: System Administrators
Classifier: License :: OSI Approved :: GNU General Public License (GPL)
Classifier: Natural Language :: Russian
Classifier: Operating System :: POSIX :: Linux
Classifier: Operating System :: POSIX :: BSD
Classifier: Programming Language :: Python
Classifier: Programming Language :: Python :: 2.5
Classifier: Topic :: Security
Classifier: Topic :: Communications
